wandbmon/__init__.py
wandbmon/sdk/evaluate.py
wandbmon/sdk/logging.py
wandbmon/sdk/monitor.py
wandbmon-0.1.0.dist-info/LICENSE
wandbmon-0.1.0.dist-info/METADATA
wandbmon-0.1.0.dist-info/WHEEL
wandbmon-0.1.0.dist-info/top_level.txt
wandbmon-0.1.0.dist-info/RECORD
