Metadata-Version: 2.1
Name: wandbmon
Version: 0.1.0
Summary: A library for monitoring models at inference time
Author-email: Weights & Biases <support@wandb.com>
License: Apache-2.0
Project-URL: Company, https://wandb.com
Project-URL: Documentation, https://docs.wandb.com/
Project-URL: Changes, https://github.com/wandb/wandbmon/releases
Project-URL: Source Code, https://github.com/wandb/wandbmon
Project-URL: Issue Tracker, https://github.com/wandb/wandbmon/issues/
Project-URL: Twitter, https://twitter.com/weights_biases
Classifier: Development Status :: 4 - Beta
Classifier: Environment :: Web Environment
Classifier: Intended Audience :: Developers
Classifier: Intended Audience :: Science/Research
Classifier: License :: OSI Approved :: Apache Software License
Classifier: Operating System :: OS Independent
Classifier: Programming Language :: Python
Classifier: Topic :: Database :: Front-Ends
Classifier: Topic :: Scientific/Engineering :: Information Analysis
Classifier: Topic :: Scientific/Engineering :: Visualization
Classifier: Topic :: Software Development :: Widget Sets
Requires-Python: >=3.9
License-File: LICENSE
Requires-Dist: wandb (>=0.15.2)
Provides-Extra: vision
Requires-Dist: Pillow ; extra == 'vision'
